{"cameraMode":{"drawMode":0,"name":"Shaded","section":"Shading Mode"},"sceneLighting":true,"audioPlay":false,"sceneViewState":{"showFog":true,"showMaterialUpdate":false,"showSkybox":true,"showFlares":true,"showImageEffects":true,"showParticleSystems":true},"in2DMode":false,"pivot":{"x":-2.397702693939209,"y":9.089513778686524,"z":2.6500320434570314},"rotation":{"x":0.13458451628684998,"y":0.01756872981786728,"z":-0.0025557137560099365,"w":0.9909291863441467},"size":6.861554145812988,"orthographic":false}